modify_range.py
modify_range-0.0.2.dist-info/LICENSE.txt
modify_range-0.0.2.dist-info/METADATA
modify_range-0.0.2.dist-info/WHEEL
modify_range-0.0.2.dist-info/top_level.txt
modify_range-0.0.2.dist-info/RECORD
