Metadata-Version: 2.1
Name: modify-range
Version: 0.0.2
Summary: Modify the range of collection of numbers on scale of log5 for better visualization. It works best between 0-100. max,min is the max and min value from the present list and, a and b are the max and min values you want. It will set values between a and b. Then convert it to the scale of log5
Home-page: UNKNOWN
Author: bakharia
Author-email: bakharia1@gmail.com
License: UNKNOWN
Platform: UNKNOWN
Classifier: Programming Language :: Python :: 3
Classifier: Programming Language :: Python :: 3.6
Classifier: Programming Language :: Python :: 3.7
Classifier: Programming Language :: Python :: 3.8
Classifier: License :: OSI Approved :: MIT License
Classifier: Operating System :: OS Independent
